beastify/__init__.py
beastify/__main__.py
beastify/nexus/Collection.py
beastify/nexus/Genes.py
beastify/nexus/Isolate.py
beastify/nexus/__init__.py
beastify/nexus/tests/Test_Nexus.py
beastify/nexus/tests/__init__.py
beastify/test_data/test.fasta
beastify/test_data/test.gbk
beastify/test_data/test.gff
beastify/test_data/test.nexus
beastify/test_data/test.phy
beastify/test_data/test_data.R
beastify/test_data/test_multi.fasta
beastify/test_data/test_reorder_multi.fasta
beastify-0.2.0a0.dist-info/METADATA
beastify-0.2.0a0.dist-info/RECORD
beastify-0.2.0a0.dist-info/WHEEL
beastify-0.2.0a0.dist-info/entry_points.txt
beastify-0.2.0a0.dist-info/top_level.txt
