Metadata-Version: 2.1
Name: beastify
Version: 0.2.0a0
Summary: Partition your alignment into distinct codon positions and non-coding positions
Home-page: https://github.com/andersgs/beastify
Author: Anders Gonçalves da Silva
Author-email: andersgs@gmail.com
License: UNKNOWN
Platform: UNKNOWN
Classifier: License :: OSI Approved :: GNU Lesser General Public License v3 (LGPLv3)
Classifier: Programming Language :: Python :: 3
Classifier: Programming Language :: Python :: 3.6
Classifier: Programming Language :: Python :: 3.7
Requires-Dist: click
Requires-Dist: pandas
Requires-Dist: numpy
Requires-Dist: biopython
